conf/__init__.py
conf/logger.yaml
dna/__init__.py
dna/color.py
dna/config.py
dna/execution.py
dna/size2d.py
dna/size2di.py
dna/types.py
dna/utils.py
dna/zone.py
dna/camera/__init__.py
dna/camera/camera.py
dna/camera/ffmpeg_camera.py
dna/camera/ffmpeg_writer.py
dna/camera/image_processor.py
dna/camera/opencv_camera.py
dna/camera/opencv_video_writer.py
dna/camera/ts_generator.py
dna/camera/types.py
dna/camera/utils.py
dna/detect/__init__.py
dna/detect/detecting_processor.py
dna/detect/detection.py
dna/detect/object_detector.py
dna/detect/utils.py
dna/detect/rcnn50_fpn/__init__.py
dna/detect/rcnn50_fpn/rcnn50_fpn_detector.py
dna/detect/rcnn50_fpn_v2/__init__.py
dna/detect/rcnn50_fpn_v2/rcnn50_fpn_v2_detector.py
dna/detect/ultralytics/__init__.py
dna/detect/ultralytics/ultralytics_detector.py
dna/detect/yolov4/__init__.py
dna/detect/yolov4/yolov4_detector.py
dna/detect/yolov4/tool/__init__.py
dna/detect/yolov4/tool/camera.py
dna/detect/yolov4/tool/coco_annotation.py
dna/detect/yolov4/tool/config.py
dna/detect/yolov4/tool/darknet2onnx.py
dna/detect/yolov4/tool/darknet2pytorch.py
dna/detect/yolov4/tool/onnx2tensorflow.py
dna/detect/yolov4/tool/region_loss.py
dna/detect/yolov4/tool/torch_utils.py
dna/detect/yolov4/tool/utils.py
dna/detect/yolov4/tool/utils_iou.py
dna/detect/yolov4/tool/utils_iou_test.py
dna/detect/yolov4/tool/yolo_layer.py
dna/detect/yolov5/__init__.py
dna/detect/yolov5/yolov5_detector.py
dna/event/__init__.py
dna/event/event_node_pipeline.py
dna/event/event_processor.py
dna/event/event_processors.py
dna/event/json_event.py
dna/event/kafka_utils.py
dna/event/local_path_event.py
dna/event/multi_stage_pipeline.py
dna/event/tracklet_store.py
dna/event/types.py
dna/event/utils.py
dna/event/proto/__init__.py
dna/event/proto/reid_feature_pb2.py
dna/event/proto/reid_feature_pb2_grpc.py
dna/node/__init__.py
dna/node/drop_short_trail.py
dna/node/global_track.py
dna/node/kafka_event_publisher.py
dna/node/local_path_generator.py
dna/node/node_event_pipeline.py
dna.node-2024.1.16.dist-info/METADATA
dna.node-2024.1.16.dist-info/WHEEL
dna.node-2024.1.16.dist-info/entry_points.txt
dna.node-2024.1.16.dist-info/top_level.txt
dna.node-2024.1.16.dist-info/RECORD
